{"trial_id": "09", "hyperparameters": {"space": [{"class_name": "Int", "config": {"name": "num_layers", "default": null, "conditions": [], "min_value": 1, "max_value": 9, "step": 1, "sampling": "linear"}}, {"class_name": "Int", "config": {"name": "units_0", "default": null, "conditions": [], "min_value": 4, "max_value": 256, "step": 4, "sampling": "linear"}}, {"class_name": "Choice", "config": {"name": "activation_0", "default": "relu", "conditions": [], "values": ["relu", "elu", "selu"], "ordered": false}}, {"class_name": "Float", "config": {"name": "l2_0", "default": 0.0001, "conditions": [], "min_value": 0.0001, "max_value": 0.01, "step": null, "sampling": "log"}}, {"class_name": "Float", "config": {"name": "learning_rate", "default": 0.0001, "conditions": [], "min_value": 0.0001, "max_value": 0.1, "step": null, "sampling": "log"}}, {"class_name": "Choice", "config": {"name": "optimizer", "default": "adam", "conditions": [], "values": ["adam", "rmsprop"], "ordered": false}}, {"class_name": "Int", "config": {"name": "units_1", "default": null, "conditions": [], "min_value": 4, "max_value": 256, "step": 4, "sampling": "linear"}}, {"class_name": "Choice", "config": {"name": "activation_1", "default": "relu", "conditions": [], "values": ["relu", "elu", "selu"], "ordered": false}}, {"class_name": "Float", "config": {"name": "l2_1", "default": 0.0001, "conditions": [], "min_value": 0.0001, "max_value": 0.01, "step": null, "sampling": "log"}}, {"class_name": "Int", "config": {"name": "units_2", "default": null, "conditions": [], "min_value": 4, "max_value": 256, "step": 4, "sampling": "linear"}}, {"class_name": "Choice", "config": {"name": "activation_2", "default": "relu", "conditions": [], "values": ["relu", "elu", "selu"], "ordered": false}}, {"class_name": "Float", "config": {"name": "l2_2", "default": 0.0001, "conditions": [], "min_value": 0.0001, "max_value": 0.01, "step": null, "sampling": "log"}}, {"class_name": "Int", "config": {"name": "units_3", "default": null, "conditions": [], "min_value": 4, "max_value": 256, "step": 4, "sampling": "linear"}}, {"class_name": "Choice", "config": {"name": "activation_3", "default": "relu", "conditions": [], "values": ["relu", "elu", "selu"], "ordered": false}}, {"class_name": "Float", "config": {"name": "l2_3", "default": 0.0001, "conditions": [], "min_value": 0.0001, "max_value": 0.01, "step": null, "sampling": "log"}}, {"class_name": "Int", "config": {"name": "units_4", "default": null, "conditions": [], "min_value": 4, "max_value": 256, "step": 4, "sampling": "linear"}}, {"class_name": "Choice", "config": {"name": "activation_4", "default": "relu", "conditions": [], "values": ["relu", "elu", "selu"], "ordered": false}}, {"class_name": "Float", "config": {"name": "l2_4", "default": 0.0001, "conditions": [], "min_value": 0.0001, "max_value": 0.01, "step": null, "sampling": "log"}}, {"class_name": "Int", "config": {"name": "units_5", "default": null, "conditions": [], "min_value": 4, "max_value": 256, "step": 4, "sampling": "linear"}}, {"class_name": "Choice", "config": {"name": "activation_5", "default": "relu", "conditions": [], "values": ["relu", "elu", "selu"], "ordered": false}}, {"class_name": "Float", "config": {"name": "l2_5", "default": 0.0001, "conditions": [], "min_value": 0.0001, "max_value": 0.01, "step": null, "sampling": "log"}}, {"class_name": "Int", "config": {"name": "units_6", "default": null, "conditions": [], "min_value": 4, "max_value": 256, "step": 4, "sampling": "linear"}}, {"class_name": "Choice", "config": {"name": "activation_6", "default": "relu", "conditions": [], "values": ["relu", "elu", "selu"], "ordered": false}}, {"class_name": "Float", "config": {"name": "l2_6", "default": 0.0001, "conditions": [], "min_value": 0.0001, "max_value": 0.01, "step": null, "sampling": "log"}}, {"class_name": "Int", "config": {"name": "units_7", "default": null, "conditions": [], "min_value": 4, "max_value": 256, "step": 4, "sampling": "linear"}}, {"class_name": "Choice", "config": {"name": "activation_7", "default": "relu", "conditions": [], "values": ["relu", "elu", "selu"], "ordered": false}}, {"class_name": "Float", "config": {"name": "l2_7", "default": 0.0001, "conditions": [], "min_value": 0.0001, "max_value": 0.01, "step": null, "sampling": "log"}}, {"class_name": "Int", "config": {"name": "units_8", "default": null, "conditions": [], "min_value": 4, "max_value": 256, "step": 4, "sampling": "linear"}}, {"class_name": "Choice", "config": {"name": "activation_8", "default": "relu", "conditions": [], "values": ["relu", "elu", "selu"], "ordered": false}}, {"class_name": "Float", "config": {"name": "l2_8", "default": 0.0001, "conditions": [], "min_value": 0.0001, "max_value": 0.01, "step": null, "sampling": "log"}}], "values": {"num_layers": 9, "units_0": 36, "activation_0": "selu", "l2_0": 0.002357749114585103, "learning_rate": 0.01299880992037507, "optimizer": "rmsprop", "units_1": 28, "activation_1": "elu", "l2_1": 0.0009213238138088548, "units_2": 156, "activation_2": "relu", "l2_2": 0.004071051060895889, "units_3": 72, "activation_3": "selu", "l2_3": 0.005046956045491829, "units_4": 92, "activation_4": "relu", "l2_4": 0.0003005119239919036, "units_5": 160, "activation_5": "selu", "l2_5": 0.008324915131264987, "units_6": 108, "activation_6": "relu", "l2_6": 0.0067935411191000555, "units_7": 208, "activation_7": "relu", "l2_7": 0.00010809141393756479, "units_8": 4, "activation_8": "relu", "l2_8": 0.0001}}, "metrics": {"metrics": {"loss": {"direction": "min", "observations": [{"value": [1.912334680557251], "step": 45}]}, "mae": {"direction": "min", "observations": [{"value": [1.912334680557251], "step": 45}]}, "val_loss": {"direction": "min", "observations": [{"value": [1.919671893119812], "step": 45}]}, "val_mae": {"direction": "min", "observations": [{"value": [1.919671893119812], "step": 45}]}, "learning_rate": {"direction": "min", "observations": [{"value": [5.077660171082243e-05], "step": 45}]}}}, "score": 1.919671893119812, "best_step": 45, "status": "COMPLETED", "message": null}