{"ongoing_trials": {"tuner0": "004"}, "hyperparameters": {"space": [{"class_name": "Int", "config": {"name": "num_layers", "default": null, "conditions": [], "min_value": 2, "max_value": 5, "step": 1, "sampling": "linear"}}, {"class_name": "Int", "config": {"name": "units_0", "default": null, "conditions": [], "min_value": 1, "max_value": 32, "step": 1, "sampling": "linear"}}, {"class_name": "Int", "config": {"name": "grid_size_0", "default": null, "conditions": [], "min_value": 3, "max_value": 7, "step": 1, "sampling": "linear"}}, {"class_name": "Int", "config": {"name": "spline_order_0", "default": null, "conditions": [], "min_value": 2, "max_value": 4, "step": 1, "sampling": "linear"}}, {"class_name": "Int", "config": {"name": "units_1", "default": null, "conditions": [], "min_value": 1, "max_value": 32, "step": 1, "sampling": "linear"}}, {"class_name": "Int", "config": {"name": "grid_size_1", "default": null, "conditions": [], "min_value": 3, "max_value": 7, "step": 1, "sampling": "linear"}}, {"class_name": "Int", "config": {"name": "spline_order_1", "default": null, "conditions": [], "min_value": 2, "max_value": 4, "step": 1, "sampling": "linear"}}, {"class_name": "Float", "config": {"name": "learning_rate", "default": 0.0001, "conditions": [], "min_value": 0.0001, "max_value": 0.01, "step": null, "sampling": "log"}}, {"class_name": "Choice", "config": {"name": "optimizer", "default": "adam", "conditions": [], "values": ["adam", "adagrad", "rmsprop", "adadelta"], "ordered": false}}, {"class_name": "Int", "config": {"name": "units_2", "default": null, "conditions": [], "min_value": 1, "max_value": 32, "step": 1, "sampling": "linear"}}, {"class_name": "Int", "config": {"name": "grid_size_2", "default": null, "conditions": [], "min_value": 3, "max_value": 7, "step": 1, "sampling": "linear"}}, {"class_name": "Int", "config": {"name": "spline_order_2", "default": null, "conditions": [], "min_value": 2, "max_value": 4, "step": 1, "sampling": "linear"}}, {"class_name": "Int", "config": {"name": "units_3", "default": null, "conditions": [], "min_value": 1, "max_value": 32, "step": 1, "sampling": "linear"}}, {"class_name": "Int", "config": {"name": "grid_size_3", "default": null, "conditions": [], "min_value": 3, "max_value": 7, "step": 1, "sampling": "linear"}}, {"class_name": "Int", "config": {"name": "spline_order_3", "default": null, "conditions": [], "min_value": 2, "max_value": 4, "step": 1, "sampling": "linear"}}], "values": {"num_layers": 2, "units_0": 1, "grid_size_0": 3, "spline_order_0": 2, "units_1": 1, "grid_size_1": 3, "spline_order_1": 2, "learning_rate": 0.0001, "optimizer": "adam", "units_2": 1, "grid_size_2": 3, "spline_order_2": 2, "units_3": 1, "grid_size_3": 3, "spline_order_3": 2}}, "start_order": ["000", "001", "002", "003", "004"], "end_order": ["000", "001", "002", "003"], "run_times": {"000": 1, "001": 1, "002": 1, "003": 1}, "retry_queue": [], "seed": 6312, "seed_state": 6375, "tried_so_far": ["c313fe0bdc744227093d0be908b0e8ab", "ae8e7d211c016c867cc53bf554e49abe", "d8f67a551a28b845c8e3dcc01ce91c03", "92b41b39df57715810ac73f1b9e8b5e6", "7c81736f0e2e61e8a7dda94fbba3d091"], "id_to_hash": {"000": "d8f67a551a28b845c8e3dcc01ce91c03", "001": "7c81736f0e2e61e8a7dda94fbba3d091", "002": "92b41b39df57715810ac73f1b9e8b5e6", "003": "ae8e7d211c016c867cc53bf554e49abe", "004": "c313fe0bdc744227093d0be908b0e8ab"}, "display": {"search_start": "2024-07-06T10:06:12.980608", "trial_start": {"000": "2024-07-06T10:06:12.980608", "001": "2024-07-06T10:14:38.417230", "002": "2024-07-06T10:23:34.677422", "003": "2024-07-06T10:30:06.119776"}, "trial_number": {"000": 1, "001": 2, "002": 3, "003": 4}}, "num_initial_points": null, "alpha": 0.0001, "beta": 2.6}